fsarcamp/__init__.py
fsarcamp/campaign_utils.py
fsarcamp/common.py
fsarcamp/dataframe.py
fsarcamp/fs_utils.py
fsarcamp/fsar_parameters.py
fsarcamp/interpolation.py
fsarcamp/lookup.py
fsarcamp/multilook.py
fsarcamp/pauli_rgb.py
fsarcamp/polsar.py
fsarcamp/slantrange2geo.py
fsarcamp/windowed_geocoding.py
fsarcamp/_experimental/__init__.py
fsarcamp/_experimental/cropex14_passes.py
fsarcamp/_experimental/cropex25_passes.py
fsarcamp/_experimental/hterra22_passes.py
fsarcamp/cropex14/__init__.py
fsarcamp/cropex14/biomass.py
fsarcamp/cropex14/dates.py
fsarcamp/cropex14/fsar.py
fsarcamp/cropex14/moisture.py
fsarcamp/cropex14/regions.py
fsarcamp/cropex25/__init__.py
fsarcamp/cropex25/dates.py
fsarcamp/cropex25/fsar.py
fsarcamp/cropex25/moisture.py
fsarcamp/cropex25/regions.py
fsarcamp/hterra22/__init__.py
fsarcamp/hterra22/dates.py
fsarcamp/hterra22/fsar.py
fsarcamp/hterra22/moisture.py
fsarcamp/hterra22/regions.py
fsarcamp/ste_io/__init__.py
fsarcamp/ste_io/ste_io.py
fsarcamp-3.1.1.dist-info/licenses/LICENSE
fsarcamp-3.1.1.dist-info/METADATA
fsarcamp-3.1.1.dist-info/WHEEL
fsarcamp-3.1.1.dist-info/top_level.txt
fsarcamp-3.1.1.dist-info/RECORD
