Metadata-Version: 2.4
Name: fsarcamp
Version: 3.1.1
Summary: Data loaders for selected F-SAR campaigns
Author-email: Nikita Basargin <nikita.basargin@dlr.de>
License: MIT License
Requires-Python: >=3.10
License-File: LICENSE
Requires-Dist: numpy
Requires-Dist: scipy
Requires-Dist: shapely
Requires-Dist: matplotlib
Requires-Dist: pandas
Requires-Dist: openpyxl
Requires-Dist: geopandas
Requires-Dist: rasterio
Requires-Dist: pyproj
Dynamic: license-file
